psybee-0.1.6.dist-info/RECORD
psybee-0.1.6.dist-info/WHEEL
psybee-0.1.6.dist-info/METADATA
psybee/psybee.pypy310-pp73-darwin.so
psybee/__init__.py
psybee/.dylibs/libgstreamer-1.0.0.dylib
psybee/.dylibs/libpcre2-8.0.dylib
psybee/.dylibs/libglib-2.0.0.dylib
psybee/.dylibs/libgobject-2.0.0.dylib
psybee/.dylibs/libgstvideo-1.0.0.dylib
psybee/.dylibs/libgstapp-1.0.0.dylib
psybee/.dylibs/libgmodule-2.0.0.dylib
psybee/.dylibs/libintl.8.dylib
psybee/.dylibs/libgstbase-1.0.0.dylib
psybee/.dylibs/libffi.7.dylib
psybee/.dylibs/liborc-0.4.0.dylib
psybee/.dylibs/libz.1.dylib
psybee/.dylibs/libgio-2.0.0.dylib
